fixreprod.py
fixreprod-0.0.11.dist-info/METADATA
fixreprod-0.0.11.dist-info/WHEEL
fixreprod-0.0.11.dist-info/entry_points.txt
fixreprod-0.0.11.dist-info/top_level.txt
fixreprod-0.0.11.dist-info/RECORD
