Metadata-Version: 2.1
Name: fixreprod
Version: 0.0.11
Summary: A package for showing all seeds to be fixed
Home-page: https://github.com/y-takefuji/fixreprod
Author: yoshiyasu takefuji
Author-email: takefuji@keio.jp
License: UNKNOWN
Project-URL: Bug Tracker, https://github.com/y-takefuji/fixreprod
Platform: UNKNOWN
Classifier: Programming Language :: Python :: 3
Classifier: License :: OSI Approved :: MIT License
Classifier: Operating System :: OS Independent
Requires-Python: >=3.8
